utils/__init__.py
utils_nuuuwan-2.0.11.dist-info/LICENSE
utils_nuuuwan-2.0.11.dist-info/METADATA
utils_nuuuwan-2.0.11.dist-info/WHEEL
utils_nuuuwan-2.0.11.dist-info/top_level.txt
utils_nuuuwan-2.0.11.dist-info/RECORD
