Metadata-Version: 2.1
Name: utils-nuuuwan
Version: 2.0.11
Summary: Utilities, complementing the Python Standard Library
Home-page: https://github.com/nuuuwan/utils
Author: Nuwan I. Senaratna
Author-email: nuuuwan@gmail.com
Project-URL: Bug Tracker, https://github.com/nuuuwan/utils/issues
Classifier: Programming Language :: Python :: 3
Classifier: License :: OSI Approved :: MIT License
Classifier: Operating System :: OS Independent
Requires-Python: >=3.10
License-File: LICENSE
Requires-Dist: utils-ai-nuuuwan
Requires-Dist: utils-base-nuuuwan
Requires-Dist: utils-git-nuuuwan
Requires-Dist: utils-lang-nuuuwan
Requires-Dist: utils-twitter-nuuuwan
Requires-Dist: utils-www-nuuuwan
